nlptriples/__init__.py
nlptriples/parse_tree.py
nlptriples/setup.py
nlptriples/triples.py
nlptriples-0.1.7.dist-info/LICENSE
nlptriples-0.1.7.dist-info/WHEEL
nlptriples-0.1.7.dist-info/METADATA
nlptriples-0.1.7.dist-info/RECORD
